wt_blk_pybindings-0.2.1.dist-info/METADATA
wt_blk_pybindings-0.2.1.dist-info/WHEEL
wt_blk_pybindings/__init__.py
wt_blk_pybindings/__init__.pyi
wt_blk_pybindings/py.typed
wt_blk_pybindings/wt_blk_pybindings.cpython-39-arm-linux-gnueabihf.so
wt_blk_pybindings-0.2.1.dist-info/RECORD
