Metadata-Version: 2.4
Name: wt_blk_pybindings
Version: 0.2.1
